odoo10_addon_l10n_fi_business_code_validate-10.0.1.2.5.99.dev1-py2.7-nspkg.pth
odoo/addons/l10n_fi_business_code_validate/README.rst
odoo/addons/l10n_fi_business_code_validate/__init__.py
odoo/addons/l10n_fi_business_code_validate/__manifest__.py
odoo/addons/l10n_fi_business_code_validate/data/res_partner_id_category.xml
odoo/addons/l10n_fi_business_code_validate/i18n/fi.po
odoo/addons/l10n_fi_business_code_validate/i18n/l10n_fi_business_code_validate.pot
odoo/addons/l10n_fi_business_code_validate/models/__init__.py
odoo/addons/l10n_fi_business_code_validate/models/res_partner_id_category.py
odoo/addons/l10n_fi_business_code_validate/static/description/icon.png
odoo/addons/l10n_fi_business_code_validate/tests/__init__.py
odoo/addons/l10n_fi_business_code_validate/tests/test_business_id_validate.py
odoo10_addon_l10n_fi_business_code_validate-10.0.1.2.5.99.dev1.dist-info/METADATA
odoo10_addon_l10n_fi_business_code_validate-10.0.1.2.5.99.dev1.dist-info/RECORD
odoo10_addon_l10n_fi_business_code_validate-10.0.1.2.5.99.dev1.dist-info/WHEEL
odoo10_addon_l10n_fi_business_code_validate-10.0.1.2.5.99.dev1.dist-info/namespace_packages.txt
odoo10_addon_l10n_fi_business_code_validate-10.0.1.2.5.99.dev1.dist-info/top_level.txt
