Metadata-Version: 2.1
Name: odoo10-addon-l10n-fi-business-code-validate
Version: 10.0.1.2.5.99.dev1
Summary: Adds validation for partner_business_code
Home-page: https://odoo-community.org/
Author: Oy Tawasta Technologies Ltd., Odoo Community Association (OCA)
Author-email: support@odoo-community.org
License: AGPL-3
Platform: UNKNOWN
Classifier: Programming Language :: Python
Classifier: Framework :: Odoo
Classifier: License :: OSI Approved :: GNU Affero General Public License v3
Requires-Python: ~=2.7
Requires-Dist: odoo10-addon-l10n-fi-business-code
Requires-Dist: odoo (<10.1dev,>=10.0)
